abusive_error_messages/__init__.py
abusive_error_messages-1.0.1.dist-info/METADATA
abusive_error_messages-1.0.1.dist-info/WHEEL
abusive_error_messages-1.0.1.dist-info/licenses/LICENSE.txt
abusive_error_messages-1.0.1.dist-info/RECORD
