Metadata-Version: 2.3
Name: abusive-error-messages
Version: 1.0.1
Summary: Because programming isn't hard enough already
Project-URL: Documentation, https://github.com/unknown/abusive-error-messages#readme
Project-URL: Issues, https://github.com/unknown/abusive-error-messages/issues
Project-URL: Source, https://github.com/unknown/abusive-error-messages
Author-email: Copeland Carter <smartycope@gmail.com>
License-Expression: MIT
License-File: LICENSE.txt
Classifier: Development Status :: 4 - Beta
Classifier: Programming Language :: Python
Classifier: Programming Language :: Python :: 3.8
Classifier: Programming Language :: Python :: 3.9
Classifier: Programming Language :: Python :: 3.10
Classifier: Programming Language :: Python :: 3.11
Classifier: Programming Language :: Python :: 3.12
Classifier: Programming Language :: Python :: Implementation :: CPython
Classifier: Programming Language :: Python :: Implementation :: PyPy
Requires-Python: >=3.8
Requires-Dist: rich
